minimal_dydb/__init__.py
minimal_dydb/_aws_auth.py
minimal_dydb/_config.py
minimal_dydb/_credential_managers.py
minimal_dydb/_dydb.py
minimal_dydb-0.1.16.dist-info/LICENSE
minimal_dydb-0.1.16.dist-info/WHEEL
minimal_dydb-0.1.16.dist-info/METADATA
minimal_dydb-0.1.16.dist-info/RECORD
